example/NMSTPP_data.py
example/statsbomb_skillcorner.py
openstarlab_preprocessing-0.1.43.dist-info/licenses/LICENSE.md
preprocessing/__init__.py
preprocessing/common.py
preprocessing/config.py
preprocessing/pytest/pytest_init.py
preprocessing/sports/__init__.py
preprocessing/sports/SAR_data/SAR_class.py
preprocessing/sports/SAR_data/__init__.py
preprocessing/sports/SAR_data/pytest_SAR_class.py
preprocessing/sports/SAR_data/soccer/__init__.py
preprocessing/sports/SAR_data/soccer/constant.py
preprocessing/sports/SAR_data/soccer/dataclass.py
preprocessing/sports/SAR_data/soccer/env.py
preprocessing/sports/SAR_data/soccer/soccer_SAR_class.py
preprocessing/sports/SAR_data/soccer/soccer_SAR_cleaning.py
preprocessing/sports/SAR_data/soccer/soccer_SAR_processing.py
preprocessing/sports/SAR_data/soccer/soccer_SAR_state.py
preprocessing/sports/SAR_data/soccer/soccer_load_data.py
preprocessing/sports/SAR_data/soccer/cleaning/clean_data.py
preprocessing/sports/SAR_data/soccer/cleaning/clean_event_data.py
preprocessing/sports/SAR_data/soccer/cleaning/clean_tracking_data.py
preprocessing/sports/SAR_data/soccer/cleaning/map_column_names.py
preprocessing/sports/SAR_data/soccer/state_preprocess/epv.py
preprocessing/sports/SAR_data/soccer/state_preprocess/preprocess_frame.py
preprocessing/sports/SAR_data/soccer/state_preprocess/reward_model.py
preprocessing/sports/SAR_data/soccer/state_preprocess/state_edms.py
preprocessing/sports/SAR_data/soccer/utils/__init__.py
preprocessing/sports/SAR_data/soccer/utils/file_utils.py
preprocessing/sports/event_data/__init__.py
preprocessing/sports/event_data/event_class.py
preprocessing/sports/event_data/rocket_league/__init__.py
preprocessing/sports/event_data/rocket_league/rocket_league_event_class.py
preprocessing/sports/event_data/rocket_league/rocket_league_load_data.py
preprocessing/sports/event_data/rocket_league/rocket_league_processing.py
preprocessing/sports/event_data/soccer/__init__.py
preprocessing/sports/event_data/soccer/constant.py
preprocessing/sports/event_data/soccer/soccer_event_class.py
openstarlab_preprocessing-0.1.43.dist-info/METADATA
openstarlab_preprocessing-0.1.43.dist-info/WHEEL
openstarlab_preprocessing-0.1.43.dist-info/top_level.txt
openstarlab_preprocessing-0.1.43.dist-info/RECORD
