Metadata-Version: 2.4
Name: openstarlab_preprocessing
Version: 0.1.43
Summary: openstarlab preprocessing package
Author-email: Calvin Yeung <yeung.chikwong@g.sp.m.is.nagoya-u.ac.jp>
License: Apache License 2.0
Project-URL: Homepage, https://github.com/open-starlab/PreProcessing
Classifier: Programming Language :: Python :: 3
Classifier: License :: OSI Approved :: Apache Software License
Classifier: Operating System :: OS Independent
Requires-Python: >=3.8
License-File: LICENSE.md
Requires-Dist: ai2-tango
Requires-Dist: pandas>=1.3.0
Requires-Dist: numpy>=1.23.0
Requires-Dist: statsbombpy>=0.0.1
Requires-Dist: matplotlib>=3.7.5
Requires-Dist: tqdm
Requires-Dist: chardet>=5.2.0
Requires-Dist: jsonlines>=3.1.0
Requires-Dist: bidict>=0.22.1
Requires-Dist: pydantic>=2.9.0
Requires-Dist: scipy==1.10.1
Requires-Dist: shapely>=2.0.0
Requires-Dist: pyarrow<20.0.0,>=4.0.0
Requires-Dist: datasets>=3.0.1
Requires-Dist: gdown
Dynamic: license-file
